aleksis/core/__init__.py
aleksis/core/__main__.py
aleksis/core/admin.py
aleksis/core/apps.py
aleksis/core/celery.py
aleksis/core/checks.py
aleksis/core/data_checks.py
aleksis/core/decorators.py
aleksis/core/filters.py
aleksis/core/forms.py
aleksis/core/frontend/app/apollo.js
aleksis/core/frontend/app/dateTimeFormats.js
aleksis/core/frontend/app/i18n.js
aleksis/core/frontend/app/router.js
aleksis/core/frontend/app/sentry.js
aleksis/core/frontend/app/vuetify.js
aleksis/core/frontend/collections.js
aleksis/core/frontend/components/LegacyBaseTemplate.vue
aleksis/core/frontend/components/Parent.vue
aleksis/core/frontend/components/about/About.vue
aleksis/core/frontend/components/about/AboutAleksis.vue
aleksis/core/frontend/components/about/InstalledAppCard.vue
aleksis/core/frontend/components/about/InstalledAppsList.vue
aleksis/core/frontend/components/about/installedApps.graphql
aleksis/core/frontend/components/announcements/Announcements.vue
aleksis/core/frontend/components/announcements/announcements.graphql
aleksis/core/frontend/components/app/AccountMenu.vue
aleksis/core/frontend/components/app/App.vue
aleksis/core/frontend/components/app/BrandLogo.vue
aleksis/core/frontend/components/app/ErrorPage.vue
aleksis/core/frontend/components/app/LanguageForm.vue
aleksis/core/frontend/components/app/SideNav.vue
aleksis/core/frontend/components/app/SidenavSearch.vue
aleksis/core/frontend/components/app/SnackbarItem.vue
aleksis/core/frontend/components/app/Splash.vue
aleksis/core/frontend/components/app/customMenu.graphql
aleksis/core/frontend/components/app/dynamicRoutes.graphql
aleksis/core/frontend/components/app/messages.graphql
aleksis/core/frontend/components/app/objectPermissions.graphql
aleksis/core/frontend/components/app/ping.graphql
aleksis/core/frontend/components/app/searchSnippets.graphql
aleksis/core/frontend/components/app/systemProperties.graphql
aleksis/core/frontend/components/app/whoAmI.graphql
aleksis_core-4.0.4.dist-info/LICENCE.rst
aleksis_core-4.0.4.dist-info/METADATA
aleksis_core-4.0.4.dist-info/WHEEL
aleksis_core-4.0.4.dist-info/entry_points.txt
aleksis_core-4.0.4.dist-info/RECORD
