Metadata-Version: 2.3
Name: AlekSIS-Core
Version: 4.0.4
Summary: AlekSIS (School Information System) — Core
License: EUPL-1.2-or-later
Keywords: SIS,education,school,digitisation,school apps
Author: Dominik George
Author-email: dominik.george@teckids.org
Maintainer: Jonathan Weth
Maintainer-email: jonathan.weth@teckids.org
Requires-Python: >=3.10,<4.0
Classifier: Development Status :: 5 - Production/Stable
Classifier: Environment :: Web Environment
Classifier: Framework :: Django :: 4.1
Classifier: Intended Audience :: Developers
Classifier: Intended Audience :: Education
Classifier: License :: Other/Proprietary License
Classifier: Programming Language :: Python :: 3
Classifier: Programming Language :: Python :: 3.10
Classifier: Programming Language :: Python :: 3.11
Classifier: Programming Language :: Python :: 3.12
Classifier: Programming Language :: Python :: 3.13
Classifier: Topic :: Education
Classifier: Topic :: Internet :: WWW/HTTP :: WSGI :: Application
Classifier: Topic :: Software Development :: Libraries :: Application Frameworks
Classifier: Typing :: Typed
Provides-Extra: ldap
Provides-Extra: s3
Provides-Extra: sentry
Requires-Dist: Celery[django,redis] (>=5.2,<6.0)
Requires-Dist: Django (>=5.1,<6.0)
Requires-Dist: Whoosh (>=2.7.4,<3.0.0)
Requires-Dist: boto3 (>=1.34.52,<2.0.0)
Requires-Dist: bs4 (>=0.0.2,<0.0.3)
Requires-Dist: calendarweek (>=0.5.0,<0.6.0)
Requires-Dist: celery-haystack-ng (>=2.0,<3.0)
Requires-Dist: celery-progress (>=0.1.0,<0.2.0)
Requires-Dist: color-contrast (>=0.1.1,<0.2.0)
Requires-Dist: colour (>=0.1.5,<0.2.0)
Requires-Dist: customidenticon (>=0.1.5,<0.2.0)
Requires-Dist: defusedxml (>=0.7.1,<0.8.0)
Requires-Dist: django-allauth (>=65.0.0,<66.0.0)
Requires-Dist: django-any-js (>=1.1,<2.0)
Requires-Dist: django-auth-ldap (>=5.1,<6.0) ; extra == "ldap"
Requires-Dist: django-bleach (>=3.0.0,<4.0.0)
Requires-Dist: django-cache-memoize (>=0.2.0,<0.3.0)
Requires-Dist: django-celery-beat (>=2.6.0,<3.0.0)
Requires-Dist: django-celery-email (>=3.0.0,<4.0.0)
Requires-Dist: django-celery-results (>=2.5.1,<3.0.0)
Requires-Dist: django-ckeditor (>=6.0.0,<7.0.0)
Requires-Dist: django-cleanup (>=9.0.0,<10.0.0)
Requires-Dist: django-colorfield (>=0.13.0,<0.14.0)
Requires-Dist: django-countries (>=7.6.1,<8.0.0)
Requires-Dist: django-dbbackup (>=4.0.0,<5.0.0)
Requires-Dist: django-dynamic-preferences (>=1.11,<2.0)
Requires-Dist: django-extensions (>=3.1.1,<4.0.0)
Requires-Dist: django-favicon-plus-reloaded (>=1.2,<2.0)
Requires-Dist: django-filter (>=25.1,<26.0)
Requires-Dist: django-guardian (>=2.2.0,<3.0.0)
Requires-Dist: django-haystack (>=3.3b2,<4.0)
Requires-Dist: django-health-check (>=3.12.1,<4.0.0)
Requires-Dist: django-ical (>=1.9.2,<2.0.0)
Requires-Dist: django-iconify (>=0.4,<0.5)
Requires-Dist: django-impersonate (>=1.4,<2.0)
Requires-Dist: django-invitations (>=2.0.0,<3.0.0)
Requires-Dist: django-ipware (>=7.0,<8.0)
Requires-Dist: django-maintenance-mode (>=0.22.0,<0.23.0)
Requires-Dist: django-material (>=1.6.0,<2.0.0)
Requires-Dist: django-model-utils (>=5.0.0,<6.0.0)
Requires-Dist: django-oauth-toolkit (>=3.0.0,<4.0.0)
Requires-Dist: django-pg-rrule (>=0.4.2,<0.5.0)
Requires-Dist: django-phonenumber-field[phonenumbers] (>=8.0,<9.0)
Requires-Dist: django-polymorphic (>=3.0.0,<4.0.0)
Requires-Dist: django-prometheus (>=2.1.0,<3.0.0)
Requires-Dist: django-recurrence (>=1.11.1,<2.0.0)
Requires-Dist: django-reversion (>=5.0.0,<6.0.0)
Requires-Dist: django-storages (>=1.14.2,<2.0.0) ; extra == "s3"
Requires-Dist: django-tables2 (>=2.1,<3.0)
Requires-Dist: django-templated-email (>=3.0.0,<4.0.0)
Requires-Dist: django-timezone-field (>=7.0,<8.0)
Requires-Dist: django-titofisto (>=1.0.0,<2.0.0)
Requires-Dist: django-two-factor-auth[call,phonenumbers,sms,webauthn] (>=1.15.1,<2.0.0)
Requires-Dist: django-uwsgi-ng (>=2.0,<3.0)
Requires-Dist: django-vite (>=3.0.6,<4.0.0)
Requires-Dist: django-yarnpkg (>=6.1.2,<7.0.0)
Requires-Dist: django_select2 (>=8.0,<9.0)
Requires-Dist: djangorestframework (>=3.12.4,<4.0.0)
Requires-Dist: dynaconf[ini,toml,yaml] (>=3.1,<4.0)
Requires-Dist: graphene-django (>=3.0.0,<=3.2.2)
Requires-Dist: graphene-django-cud (>=0.13.0,<0.14.0)
Requires-Dist: graphene-django-optimizer-reloaded (>=0.9.2,<0.10.0)
Requires-Dist: graphene-file-upload (>=1.3.0,<2.0.0)
Requires-Dist: haystack-redis (>=0.0.1,<0.0.2)
Requires-Dist: html2text (>=2025.0.0,<2026.0.0)
Requires-Dist: ipython (>=8.0.0,<9.0.0)
Requires-Dist: libsass (>=0.23.0,<0.24.0)
Requires-Dist: license-expression (>=30.0,<31.0)
Requires-Dist: psutil (>=7.0.0,<8.0.0)
Requires-Dist: psycopg (>=3.2,<4.0)
Requires-Dist: psycopg-pool (>=3.2,<4.0)
Requires-Dist: pycountry (>=24.0.0,<25.0.0)
Requires-Dist: python-gnupg (>=0.5.0,<0.6.0)
Requires-Dist: rules (>=3.0,<4.0)
Requires-Dist: selenium (>=4.4.3,<5.0.0)
Requires-Dist: sentry-sdk (>=2.0.0,<3.0.0) ; extra == "sentry"
Requires-Dist: tqdm (>=4.66.1,<5.0.0)
Requires-Dist: uwsgi (>=2.0.21,<3.0.0)
Requires-Dist: webdriver-manager (>=4.0.2,<5.0.0)
Project-URL: Documentation, https://aleksis.org/AlekSIS-Core/docs/html/
Project-URL: Homepage, https://aleksis.org
Project-URL: Repository, https://edugit.org/AlekSIS/official/AlekSIS-Core
